dlairflow/__init__.py
dlairflow/load.py
dlairflow/postgresql.py
dlairflow/scripts.py
dlairflow/util.py
dlairflow/test/__init__.py
dlairflow/test/test_load.py
dlairflow/test/test_postgresql.py
dlairflow/test/test_scripts.py
dlairflow/test/test_top_level.py
dlairflow/test/test_util.py
dlairflow-0.1.6.dist-info/licenses/LICENSE.md
dlairflow-0.1.6.dist-info/METADATA
dlairflow-0.1.6.dist-info/WHEEL
dlairflow-0.1.6.dist-info/entry_points.txt
dlairflow-0.1.6.dist-info/top_level.txt
dlairflow-0.1.6.dist-info/zip-safe
dlairflow-0.1.6.dist-info/RECORD
