Metadata-Version: 2.4
Name: dlairflow
Version: 0.1.6
Summary: Reusable code components for building Apache Airflow DAGs.
Home-page: https://github.com/astro-datalab/dlairflow
Author: Astro Data Lab
Author-email: datalab@noirlab.edu
License: BSD-3-Clause
Classifier: Development Status :: 3 - Alpha
Classifier: Environment :: Console
Classifier: Framework :: Apache Airflow
Classifier: Intended Audience :: Science/Research
Classifier: Operating System :: OS Independent
Classifier: Programming Language :: Python :: 3
Classifier: Topic :: Scientific/Engineering :: Astronomy
Classifier: Topic :: System :: Software Distribution
Classifier: Topic :: Utilities
Requires-Python: >=3.9
License-File: LICENSE.md
Requires-Dist: apache-airflow
Requires-Dist: apache-airflow-providers-postgres
Provides-Extra: test
Requires-Dist: pytest; extra == "test"
Provides-Extra: coverage
Requires-Dist: pytest-cov; extra == "coverage"
Requires-Dist: coveralls; extra == "coverage"
Provides-Extra: doc
Requires-Dist: Sphinx; extra == "doc"
Requires-Dist: sphinx-rtd-theme>1.2; extra == "doc"
Dynamic: license-file
